pyevr/__init__.py
pyevr/apis.py
pyevr/client.py
pyevr/docs/AddMeasurementActRequest.md
pyevr/docs/AddShipmentsToWaybillRequest.md
pyevr/docs/AddWaybillNoteRequest.md
pyevr/docs/Address.md
pyevr/docs/Assortment.md
pyevr/docs/AssortmentsApi.md
pyevr/docs/AuthorizationType.md
pyevr/docs/CancelWaybillRequest.md
pyevr/docs/Certificate.md
pyevr/docs/CertificateClaim.md
pyevr/docs/CertificatesApi.md
pyevr/docs/ConsolidatedAct.md
pyevr/docs/ContactPerson.md
pyevr/docs/ContractForTransferOfCuttingRights.md
pyevr/docs/Coordinates.md
pyevr/docs/Entity.md
pyevr/docs/ForestAct.md
pyevr/docs/ForestNotice.md
pyevr/docs/HoldingBase.md
pyevr/docs/InventoryAct.md
pyevr/docs/MeasurementAct.md
pyevr/docs/MeasurementUnit.md
pyevr/docs/MeasurementUnitsApi.md
pyevr/docs/MeasurementsApi.md
pyevr/docs/Organization.md
pyevr/docs/OrganizationsApi.md
pyevr/docs/Owner.md
pyevr/docs/Pack.md
pyevr/docs/PackLocation.md
pyevr/docs/PagedResultOfAssortment.md
pyevr/docs/PagedResultOfCertificate.md
pyevr/docs/PagedResultOfMeasurementAct.md
pyevr/docs/PagedResultOfMeasurementUnit.md
pyevr/docs/PagedResultOfOrganization.md
pyevr/docs/PagedResultOfPlaceOfDelivery.md
pyevr/docs/PagedResultOfWaybill.md
pyevr/docs/PlaceOfDeliveriesApi.md
pyevr/docs/PlaceOfDelivery.md
pyevr/docs/PreviousOwner.md
pyevr/docs/ProblemDetails.md
pyevr/docs/PutPlaceOfDeliveryRequest.md
pyevr/docs/Receiver.md
pyevr/docs/Representer.md
pyevr/docs/SalesContract.md
pyevr/docs/Shipment.md
pyevr/docs/ShipmentAssortment.md
pyevr/docs/ShipmentItem.md
pyevr/docs/Source.md
pyevr/docs/StartWaybillRequest.md
pyevr/docs/Total.md
pyevr/docs/Transport.md
pyevr/docs/Transporter.md
pyevr/docs/UnloadWaybillRequest.md
pyevr/docs/ValidationResult.md
pyevr/docs/Viewer.md
pyevr/docs/Waybill.md
pyevr/docs/WaybillAuthorization.md
pyevr/docs/WaybillNote.md
pyevr/docs/WaybillNoteCreator.md
pyevr/docs/WaybillPlaceOfDelivery.md
pyevr/docs/WaybillSortField.md
pyevr/docs/WaybillStatus.md
pyevr/docs/WaybillsApi.md
pyevr/docs/WithoutForestNotice.md
pyevr-0.7.0.dist-info/LICENSE
pyevr-0.7.0.dist-info/METADATA
pyevr-0.7.0.dist-info/WHEEL
pyevr-0.7.0.dist-info/RECORD
