Metadata-Version: 2.1
Name: pyevr
Version: 0.7.0
Summary: EVR API
Home-page: https://github.com/thorgate/pyevr.git
License: MIT
Keywords: OpenAPI,OpenAPI-Generator,pyevr
Author: Thorgate
Author-email: software@thorgate.eu
Requires-Python: >=3.8,<4.0
Classifier: License :: OSI Approved :: MIT License
Classifier: Programming Language :: Python :: 3
Classifier: Programming Language :: Python :: 3.8
Classifier: Programming Language :: Python :: 3.9
Classifier: Programming Language :: Python :: 3.10
Classifier: Programming Language :: Python :: 3.11
Requires-Dist: aenum (>=3.1.11)
Requires-Dist: pydantic (>=1.10.5,<2.0.0)
Requires-Dist: python-dateutil (>=2.8.2)
Requires-Dist: urllib3 (>=1.25.3)
Project-URL: Repository, https://github.com/thorgate/pyevr.git
